{"packages/cupertino_icons/assets/CupertinoIcons.ttf":["packages/cupertino_icons/assets/CupertinoIcons.ttf"],"fonts/aleyegra.ttf":["fonts/aleyegra.ttf"],"images/android_icon.jpg":["images/android_icon.jpg"],"images/apolo_screen.png":["images/apolo_screen.png"],"images/big_image.jpg":["images/big_image.jpg"],"images/database_icon.png":["images/database_icon.png"],"images/design_icon.jpg":["images/design_icon.jpg"],"images/flutter_icon.png":["images/flutter_icon.png"],"images/googleplay_icon.jpg":["images/googleplay_icon.jpg"],"images/image_second.jpg":["images/image_second.jpg"],"images/java_icon.png":["images/java_icon.png"],"images/millinews_android.png":["images/millinews_android.png"],"images/millinews_ios.png":["images/millinews_ios.png"],"images/playstore.jpg":["images/playstore.jpg"],"images/server_icon.jpg":["images/server_icon.jpg"],"images/undeuxtroissoleil_screen.png":["images/undeuxtroissoleil_screen.png"]}